lembas/__init__.py
lembas/__main__.py
lembas/_version.py
lembas/case.py
lembas/cli.py
lembas/logging.py
lembas/param.py
lembas/plugins.py
lembas/py.typed
lembas-0.1.0.dev1.dist-info/LICENSE
lembas-0.1.0.dev1.dist-info/METADATA
lembas-0.1.0.dev1.dist-info/WHEEL
lembas-0.1.0.dev1.dist-info/entry_points.txt
lembas-0.1.0.dev1.dist-info/top_level.txt
lembas-0.1.0.dev1.dist-info/RECORD
