Metadata-Version: 2.1
Name: lembas
Version: 0.1.0.dev1
Summary: Lifecycle Engineering Model-Based Analysis System
License: MIT
Requires-Python: >=3.9
License-File: LICENSE
Requires-Dist: pluggy <=1.3.0
Requires-Dist: typer <0.10
Requires-Dist: rich <14
Requires-Dist: toml
Provides-Extra: ci
Requires-Dist: lembas[dev] ; extra == 'ci'
Provides-Extra: dev
Requires-Dist: pytest <=7.4.2 ; extra == 'dev'
Requires-Dist: pytest-cov <=4.1.0 ; extra == 'dev'
Requires-Dist: mypy ; extra == 'dev'
Requires-Dist: jinja2 <3.1.3 ; extra == 'dev'
Requires-Dist: types-toml ; extra == 'dev'
Provides-Extra: docs
Requires-Dist: myst-parser ; extra == 'docs'
Requires-Dist: pydata-sphinx-theme ; extra == 'docs'
Requires-Dist: sphinx ; extra == 'docs'
Requires-Dist: sphinx-autobuild ; extra == 'docs'
Requires-Dist: sphinx-autodoc-typehints ; extra == 'docs'
Requires-Dist: toml ; extra == 'docs'
Provides-Extra: examples
Requires-Dist: planingfsi ; extra == 'examples'
Requires-Dist: pandas <=2.1.1 ; extra == 'examples'
